paka.sitemaps-1.6.1-py3.5-nspkg.pth
paka/sitemaps/__init__.py
paka/sitemaps/robots.py
paka.sitemaps-1.6.1.dist-info/DESCRIPTION.rst
paka.sitemaps-1.6.1.dist-info/METADATA
paka.sitemaps-1.6.1.dist-info/RECORD
paka.sitemaps-1.6.1.dist-info/WHEEL
paka.sitemaps-1.6.1.dist-info/metadata.json
paka.sitemaps-1.6.1.dist-info/namespace_packages.txt
paka.sitemaps-1.6.1.dist-info/top_level.txt
