Metadata-Version: 2.0
Name: paka.sitemaps
Version: 1.6.1
Summary: UNKNOWN
Home-page: https://github.com/PavloKapyshin/paka.sitemaps
Author: Pavlo Kapyshin
Author-email: i@93z.org
License: BSD
Keywords: sitemap robots
Platform: UNKNOWN
Classifier: Development Status :: 4 - Beta
Classifier: Intended Audience :: Developers
Classifier: License :: OSI Approved :: BSD License
Classifier: Programming Language :: Python :: 2
Classifier: Programming Language :: Python :: 2.7
Classifier: Programming Language :: Python :: 3
Classifier: Programming Language :: Python :: 3.5
Classifier: Programming Language :: Python :: Implementation :: CPython
Classifier: Programming Language :: Python :: Implementation :: PyPy
Requires-Dist: six
Requires-Dist: lxml
Provides-Extra: testing
